cachepath/__init__.py
cachepath-1.1.0.dist-info/AUTHORS.rst
cachepath-1.1.0.dist-info/LICENSE
cachepath-1.1.0.dist-info/METADATA
cachepath-1.1.0.dist-info/WHEEL
cachepath-1.1.0.dist-info/top_level.txt
cachepath-1.1.0.dist-info/zip-safe
cachepath-1.1.0.dist-info/RECORD
