Metadata-Version: 2.1
Name: cachepath
Version: 1.1.0
Summary: Pythonic parameterized cache paths.
Home-page: https://github.com/haydenflinner/cachepath
Author: Hayden Flinner
Author-email: hayden@flinner.me
License: MIT license
Keywords: cachepath,paths,pathlib,cache,temp
Platform: UNKNOWN
Classifier: Development Status :: 2 - Pre-Alpha
Classifier: Intended Audience :: Developers
Classifier: License :: OSI Approved :: MIT License
Classifier: Natural Language :: English
Classifier: Programming Language :: Python :: 2
Classifier: Programming Language :: Python :: 2.7
Classifier: Programming Language :: Python :: 3
Classifier: Programming Language :: Python :: 3.4
Classifier: Programming Language :: Python :: 3.5
Classifier: Programming Language :: Python :: 3.6
Classifier: Programming Language :: Python :: 3.7
